redbot_ml/__init__.py
redbot_ml/training.py
redbot_ml-0.1.0.dist-info/METADATA
redbot_ml-0.1.0.dist-info/WHEEL
redbot_ml-0.1.0.dist-info/top_level.txt
redbot_ml-0.1.0.dist-info/RECORD
