Metadata-Version: 2.4
Name: redbot_ml
Version: 0.1.0
Summary: Redbot ML module for image processing and anomaly detection
Author: Your Name
Requires-Python: >=3.8
Requires-Dist: numpy
Requires-Dist: opencv-python
Requires-Dist: torch
Requires-Dist: torchvision
Requires-Dist: Pillow
Requires-Dist: scikit-learn
Requires-Dist: scikit-image
Requires-Dist: mahotas
Requires-Dist: albumentations
Requires-Dist: matplotlib
Requires-Dist: joblib
Dynamic: author
Dynamic: requires-dist
Dynamic: requires-python
Dynamic: summary
